columnize/__init__.py
columnize/__main__.py
columnize/version.py
columnize-0.3.11.dist-info/LICENSE
columnize-0.3.11.dist-info/METADATA
columnize-0.3.11.dist-info/WHEEL
columnize-0.3.11.dist-info/top_level.txt
columnize-0.3.11.dist-info/RECORD
