Metadata-Version: 2.1
Name: columnize
Version: 0.3.11
Summary: Format a simple (i.e. not nested) list into aligned columns.
Home-page: https://github.com/rocky/pycolumnize
Author: Rocky Bernstein
Author-email: rocky@gnu.org
License: PSF2
Platform: UNKNOWN
Classifier: Development Status :: 5 - Production/Stable
Classifier: Intended Audience :: Developers
Classifier: License :: OSI Approved :: Python Software Foundation License
Classifier: Programming Language :: Python
Classifier: Topic :: Software Development :: Libraries :: Python Modules
Classifier: Programming Language :: Python :: 2.4
Classifier: Programming Language :: Python :: 2.5
Classifier: Programming Language :: Python :: 2.6
Classifier: Programming Language :: Python :: 2.7
Classifier: Programming Language :: Python :: 3.0
Classifier: Programming Language :: Python :: 3.1
Classifier: Programming Language :: Python :: 3.2
Classifier: Programming Language :: Python :: 3.3
Classifier: Programming Language :: Python :: 3.4
Classifier: Programming Language :: Python :: 3.5 
Classifier: Programming Language :: Python :: 3.6 
Classifier: Programming Language :: Python :: 3.7 
Classifier: Programming Language :: Python :: 3.8 
Classifier: Programming Language :: Python :: 3.9 
Classifier: Programming Language :: Python :: 3.10 
